[
    {
        "url": "https://api.github.com/repos/TIY-Durham/2015-FALL-FEE/issues/comments/149988700",
        "html_url": "https://github.com/TIY-Durham/2015-FALL-FEE/issues/505#issuecomment-149988700",
        "issue_url": "https://api.github.com/repos/TIY-Durham/2015-FALL-FEE/issues/505",
        "id": 149988700,
        "user": {
            "login": "s4dmw",
            "id": 13879097,
            "avatar_url": "https://avatars.githubusercontent.com/u/13879097?v=3",
            "gravatar_id": "",
            "url": "https://api.github.com/users/s4dmw",
            "html_url": "https://github.com/s4dmw",
            "followers_url": "https://api.github.com/users/s4dmw/followers",
            "following_url": "https://api.github.com/users/s4dmw/following{/other_user}",
            "gists_url": "https://api.github.com/users/s4dmw/gists{/gist_id}",
            "starred_url": "https://api.github.com/users/s4dmw/starred{/owner}{/repo}",
            "subscriptions_url": "https://api.github.com/users/s4dmw/subscriptions",
            "organizations_url": "https://api.github.com/users/s4dmw/orgs",
            "repos_url": "https://api.github.com/users/s4dmw/repos",
            "events_url": "https://api.github.com/users/s4dmw/events{/privacy}",
            "received_events_url": "https://api.github.com/users/s4dmw/received_events",
            "type": "User",
            "site_admin": false
        },
        "created_at": "2015-10-21T18:39:16Z",
        "updated_at": "2015-10-21T18:39:16Z",
        "body": "test comment 0"
    },
    {
        "url": "https://api.github.com/repos/TIY-Durham/2015-FALL-FEE/issues/comments/149989117",
        "html_url": "https://github.com/TIY-Durham/2015-FALL-FEE/issues/505#issuecomment-149989117",
        "issue_url": "https://api.github.com/repos/TIY-Durham/2015-FALL-FEE/issues/505",
        "id": 149989117,
        "user": {
            "login": "s4dmw",
            "id": 13879097,
            "avatar_url": "https://avatars.githubusercontent.com/u/13879097?v=3",
            "gravatar_id": "",
            "url": "https://api.github.com/users/s4dmw",
            "html_url": "https://github.com/s4dmw",
            "followers_url": "https://api.github.com/users/s4dmw/followers",
            "following_url": "https://api.github.com/users/s4dmw/following{/other_user}",
            "gists_url": "https://api.github.com/users/s4dmw/gists{/gist_id}",
            "starred_url": "https://api.github.com/users/s4dmw/starred{/owner}{/repo}",
            "subscriptions_url": "https://api.github.com/users/s4dmw/subscriptions",
            "organizations_url": "https://api.github.com/users/s4dmw/orgs",
            "repos_url": "https://api.github.com/users/s4dmw/repos",
            "events_url": "https://api.github.com/users/s4dmw/events{/privacy}",
            "received_events_url": "https://api.github.com/users/s4dmw/received_events",
            "type": "User",
            "site_admin": false
        },
        "created_at": "2015-10-21T18:41:00Z",
        "updated_at": "2015-10-21T18:41:00Z",
        "body": "PR's go here:"
    },
    {
        "url": "https://api.github.com/repos/TIY-Durham/2015-FALL-FEE/issues/comments/149989150",
        "html_url": "https://github.com/TIY-Durham/2015-FALL-FEE/issues/505#issuecomment-149989150",
        "issue_url": "https://api.github.com/repos/TIY-Durham/2015-FALL-FEE/issues/505",
        "id": 149989150,
        "user": {
            "login": "s4dmw",
            "id": 13879097,
            "avatar_url": "https://avatars.githubusercontent.com/u/13879097?v=3",
            "gravatar_id": "",
            "url": "https://api.github.com/users/s4dmw",
            "html_url": "https://github.com/s4dmw",
            "followers_url": "https://api.github.com/users/s4dmw/followers",
            "following_url": "https://api.github.com/users/s4dmw/following{/other_user}",
            "gists_url": "https://api.github.com/users/s4dmw/gists{/gist_id}",
            "starred_url": "https://api.github.com/users/s4dmw/starred{/owner}{/repo}",
            "subscriptions_url": "https://api.github.com/users/s4dmw/subscriptions",
            "organizations_url": "https://api.github.com/users/s4dmw/orgs",
            "repos_url": "https://api.github.com/users/s4dmw/repos",
            "events_url": "https://api.github.com/users/s4dmw/events{/privacy}",
            "received_events_url": "https://api.github.com/users/s4dmw/received_events",
            "type": "User",
            "site_admin": false
        },
        "created_at": "2015-10-21T18:41:07Z",
        "updated_at": "2015-10-21T18:41:07Z",
        "body": "test comment 1"
    },
    {
        "url": "https://api.github.com/repos/TIY-Durham/2015-FALL-FEE/issues/comments/149989164",
        "html_url": "https://github.com/TIY-Durham/2015-FALL-FEE/issues/505#issuecomment-149989164",
        "issue_url": "https://api.github.com/repos/TIY-Durham/2015-FALL-FEE/issues/505",
        "id": 149989164,
        "user": {
            "login": "s4dmw",
            "id": 13879097,
            "avatar_url": "https://avatars.githubusercontent.com/u/13879097?v=3",
            "gravatar_id": "",
            "url": "https://api.github.com/users/s4dmw",
            "html_url": "https://github.com/s4dmw",
            "followers_url": "https://api.github.com/users/s4dmw/followers",
            "following_url": "https://api.github.com/users/s4dmw/following{/other_user}",
            "gists_url": "https://api.github.com/users/s4dmw/gists{/gist_id}",
            "starred_url": "https://api.github.com/users/s4dmw/starred{/owner}{/repo}",
            "subscriptions_url": "https://api.github.com/users/s4dmw/subscriptions",
            "organizations_url": "https://api.github.com/users/s4dmw/orgs",
            "repos_url": "https://api.github.com/users/s4dmw/repos",
            "events_url": "https://api.github.com/users/s4dmw/events{/privacy}",
            "received_events_url": "https://api.github.com/users/s4dmw/received_events",
            "type": "User",
            "site_admin": false
        },
        "created_at": "2015-10-21T18:41:11Z",
        "updated_at": "2015-10-21T18:41:11Z",
        "body": "test comment 2"
    }
]
